{
  "003c10bb-0e9a-4c4b-805d-593afc9cb727": {
    "connectionRef": {
      "apiTier": "Standard",
      "displayName": "Smithsonian 3D",
      "iconUri": "https://pafeblobprodam.blob.core.windows.net/20230620t000000z717c8c38c87d43b88e2b09234086d493/ppa_5Fsmithsonian-203d_iconblob.Png?sv=2018-03-28&sr=c&sig=LhVvs1wEBMphshlVke3uEduMTjcShM9QhhHC%2FxmJRSs%3D&se=2023-06-25T20%3A00%3A00Z&sp=rl",
      "id": "/providers/microsoft.powerapps/apis/shared_ppa-5fsmithsonian-203d-5f2f2f0148e8800098",
      "isCustomApiConnection": true,
      "parameterHints": {},
      "parameterHintsV2": {}
    },
    "datasets": {},
    "dataSources": [
      "Smithsonian3D"
    ],
    "dependencies": {},
    "dependents": [],
    "id": "003c10bb-0e9a-4c4b-805d-593afc9cb727"
  },
  "c27dacb8-ddcf-4b95-b29d-d183bba9e277": {
    "connectionRef": {
      "apiTier": "Standard",
      "displayName": "Excel",
      "iconUri": "https://connectoricons-prod.azureedge.net/releases/v1.0.1623/1.0.1623.3210/excel/icon.png",
      "id": "/providers/microsoft.powerapps/apis/shared_excel",
      "parameterHints": {
        "db26807f-6e43-4edc-85db-c2ada3249858": {
          "value": "fileSource"
        }
      },
      "parameterHintsV2": {
        "fileSource": {
          "value": "db26807f-6e43-4edc-85db-c2ada3249858"
        }
      }
    },
    "datasets": {
      "b!mIuBy4hPXUG7gYpjj3vlj-7vLsRUvk5Cn1I8Ib5GzVeTICDAACgBTKfV3FECa3tR.01IJKU4H2SZAHCOD5O2NE3IUYL244OXRXG": {
        "dataSources": {
          "Coral": {
            "tableName": "Coral"
          },
          "Occupants": {
            "tableName": "Occupants"
          }
        }
      }
    },
    "dataSources": [
      "Coral",
      "Occupants"
    ],
    "dependencies": {
      "fileSource": "db26807f-6e43-4edc-85db-c2ada3249858"
    },
    "dependents": [],
    "id": "c27dacb8-ddcf-4b95-b29d-d183bba9e277"
  },
  "db26807f-6e43-4edc-85db-c2ada3249858": {
    "connectionRef": {
      "apiTier": "Standard",
      "displayName": "OneDrive dla Firm",
      "iconUri": "https://connectoricons-prod.azureedge.net/u/shgogna/globalperconnector-train1/1.0.1639.3312/onedriveforbusiness/icon.png",
      "id": "/providers/microsoft.powerapps/apis/shared_onedriveforbusiness",
      "parameterHints": {},
      "parameterHintsV2": {}
    },
    "datasets": {},
    "dataSources": [],
    "dependencies": {},
    "dependents": [
      "c27dacb8-ddcf-4b95-b29d-d183bba9e277"
    ],
    "id": "db26807f-6e43-4edc-85db-c2ada3249858"
  }
}